db2_helpers/__init__.py
db2_helpers/db2_helpers.py
db_commands/__init__.py
db_commands/db_commands.py
db_commands/db_import_export.py
db2_helpers-0.1.5.dist-info/LICENSE.txt
db2_helpers-0.1.5.dist-info/METADATA
db2_helpers-0.1.5.dist-info/WHEEL
db2_helpers-0.1.5.dist-info/entry_points.txt
db2_helpers-0.1.5.dist-info/top_level.txt
db2_helpers-0.1.5.dist-info/RECORD
