Metadata-Version: 2.1
Name: db2-helpers
Version: 0.1.5
Summary: Helper functions for managing database connections
Home-page: https://github.com/jmaenpaa/db2_helpers
Author: John Maenpaa
Author-email: johnmaenpaa@db2solutions.com
License: MIT License
Project-URL: Bug Reports, https://github.com/jmaenpaa/db2_helpers/issues
Project-URL: Source, https://github.com/jmaenpaa/db2_helpers/
Keywords: db2 ibm_db
Platform: UNKNOWN
Classifier: Development Status :: 3 - Alpha
Classifier: License :: OSI Approved :: MIT License
Classifier: Programming Language :: Python :: 3
Classifier: Programming Language :: Python :: 3.8
Classifier: Programming Language :: Python :: 3 :: Only
Requires-Python: >=3.8, <4
Requires-Dist: cryptography (>=3.3.1)
Requires-Dist: ibm-db (>=3.0.2)
Requires-Dist: click (>=7.1.2)
Provides-Extra: dev
Requires-Dist: check-manifest ; extra == 'dev'
Provides-Extra: test
Requires-Dist: coverage ; extra == 'test'
